{
	"name": "5_1_json payment type",
	"properties": {
		"folder": {
			"name": "nyc_taxi_data/discovery"
		},
		"content": {
			"query": "USE nyc_taxi_projectDB;\n\n\nselect * from \n    OPENROWSET(\n        BULK 'raw/payment_type.json',\n        DATA_SOURCE = 'nyc_taxi_data',\n        FORMAT = 'csv',\n        FIELDTERMINATOR = '0x0b',\n        FIELDQUOTE = '0x0b'\n    )with(\n        jsonread NVARCHAR(MAX)\n    )\n    as json_result_set\n\n************************************************************************************************\n\nselect JSON_VALUE(jsonread, '$.payment_type') payment_type, \nJSON_VALUE(jsonread, '$.payment_type_desc') payment_type_desc\n from \n    OPENROWSET(\n        BULK 'raw/payment_type.json',\n        DATA_SOURCE = 'nyc_taxi_data',\n        FORMAT = 'csv',\n        FIELDTERMINATOR = '0x0b',\n        FIELDQUOTE = '0x0b'\n    )with(\n        jsonread NVARCHAR(MAX)\n    )\n    as json_result_set\n\n\n    ************************************************************************************************\n\nselect CAST(JSON_VALUE(jsonread, '$.payment_type')as SMALLINT) payment_type, \nCAST (JSON_VALUE(jsonread, '$.payment_type_desc') as VARCHAR(16)) payment_type_desc\n from \n    OPENROWSET(\n        BULK 'raw/payment_type.json',\n        DATA_SOURCE = 'nyc_taxi_data',\n        FORMAT = 'csv',\n        FIELDTERMINATOR = '0x0b',\n        FIELDQUOTE = '0x0b'\n    )with(\n        jsonread NVARCHAR(MAX)\n    )\n    as json_result_set\n\n\n\n\n    ************************************************************************************************\n\nselect *\n from \n    OPENROWSET(\n        BULK 'raw/payment_type.json',\n        DATA_SOURCE = 'nyc_taxi_data',\n        FORMAT = 'csv',\n        FIELDTERMINATOR = '0x0b',\n        FIELDQUOTE = '0x0b'\n    )with(\n        jsonread NVARCHAR(MAX)\n    )\n    as json_result_set\n    CROSS APPLY openjson(jsonread)\n\n\n    ************************************************************************************************\n\nselect payment_type,payment_type_desc\n from \n    OPENROWSET(\n        BULK 'raw/payment_type.json',\n        DATA_SOURCE = 'nyc_taxi_data',\n        FORMAT = 'csv',\n        FIELDTERMINATOR = '0x0b',\n        FIELDQUOTE = '0x0b'\n    )with(\n        jsonread NVARCHAR(MAX)\n    )\n    as json_result_set\n    CROSS APPLY openjson(jsonread)with (\n        payment_type SMALLINT,\n        payment_type_desc VARCHAR(50)\n\n    );\n\n********************************************************************************************\n\n    select payment_type,payment_type_describtion\n from \n    OPENROWSET(\n        BULK 'raw/payment_type.json',\n        DATA_SOURCE = 'nyc_taxi_data',\n        FORMAT = 'csv',\n        FIELDTERMINATOR = '0x0b',\n        FIELDQUOTE = '0x0b'\n    )with(\n        jsonread NVARCHAR(MAX)\n    )\n    as json_result_set\n    CROSS APPLY openjson(jsonread)with (\n        payment_type SMALLINT,\n        payment_type_describtion VARCHAR(50) '$.payment_type_desc'\n\n    );\n\n\n    ********************************************************************************************\n\nselect CAST(JSON_VALUE(jsonread, '$.payment_type')as SMALLINT) payment_type, \nCAST (JSON_VALUE(jsonread, '$.payment_type_desc[0].value') as VARCHAR(16)) payment_type_desc,\nCAST (JSON_VALUE(jsonread, '$.payment_type_desc[1].value') as VARCHAR(16)) payment_type_describtion\n from \n    OPENROWSET(\n        BULK 'raw/payment_type_array.json',\n        DATA_SOURCE = 'nyc_taxi_data',\n        FORMAT = 'csv',\n        FIELDTERMINATOR = '0x0b',\n        FIELDQUOTE = '0x0b'\n    )with(\n        jsonread NVARCHAR(MAX)\n    )\n    as json_result_set\n\n\n    ********************************************************************************************\n\n\nselect * from \n    OPENROWSET(\n       BULK 'raw/payment_type_array.json',\n        DATA_SOURCE = 'nyc_taxi_data',\n        FORMAT = 'csv',\n        FIELDQUOTE = '0x0b',\n        FIELDTERMINATOR = '0x0b'\n    )with(\n        jsonread NVARCHAR(MAX)\n    )    as json_array_result\n    CROSS APPLY openjson(jsonread) with (\n        payment_type SMALLINT,\n        payment_type_desc NVARCHAR(MAX) as JSON \n    ) \n    CROSS APPLY openjson(payment_type_desc) with (\n        sub_type SMALLINT,\n        value NVARCHAR(15)\n    ) ;  \n\n\n\n        ********************************************************************************************\n\n\nselect payment_type,sub_type,payment_type_describtion_value from \n    OPENROWSET(\n       BULK 'raw/payment_type_array.json',\n        DATA_SOURCE = 'nyc_taxi_data',\n        FORMAT = 'csv',\n        FIELDQUOTE = '0x0b',\n        FIELDTERMINATOR = '0x0b'\n    )with(\n        jsonread NVARCHAR(MAX)\n    )    as json_array_result\n    CROSS APPLY openjson(jsonread) with (\n        payment_type SMALLINT,\n        payment_type_desc NVARCHAR(MAX) as JSON \n    ) \n    CROSS APPLY openjson(payment_type_desc) with (\n        sub_type SMALLINT,\n        payment_type_describtion_value NVARCHAR(15) '$.value'\n    ) ;  \n\n\n    \n",
			"metadata": {
				"language": "sql"
			},
			"currentConnection": {
				"databaseName": "nyc_taxi_projectDB",
				"poolName": "Built-in"
			},
			"resultLimit": 5000
		},
		"type": "SqlQuery"
	}
}